sorting_gym/__init__.py
sorting_gym/agents/__init__.py
sorting_gym/agents/scripted.py
sorting_gym/envs/__init__.py
sorting_gym/envs/basic_neural_sort_interface.py
sorting_gym/envs/functional_neural_sort_interface.py
sorting_gym/envs/sort_interface_base.py
sorting_gym/envs/tape.py
sorting_gym/envs/wrappers.py
sorting_gym/parametric_space.py
sorting_gym-0.0.9.dist-info/LICENSE.txt
sorting_gym-0.0.9.dist-info/WHEEL
sorting_gym-0.0.9.dist-info/METADATA
sorting_gym-0.0.9.dist-info/RECORD
